{
	"schemaVersion": 1,
	"id": "potato-fps",
	"version": "${version}",
	"name": "Potato FPS",
	"description": "This is an example description! Tell everyone what your mod is about!",
	"authors": [
		"Me!"
	],
	"contact": {
		"homepage": "https://fabricmc.net/",
		"sources": "https://github.com/FabricMC/fabric-example-mod"
	},
	"license": "CC0-1.0",
	"icon": "assets/potato-fps/icon.png",
	"environment": "client",
	"entrypoints": {
		"main": [
			"com.example.potatofps.PotatoFPS"
		],
		"client": [
			"com.example.potatofps.PotatoFPSClient"
		]
	},
	"mixins": [
		"potato-fps.mixins.json",
		{
			"config": "potato-fps.client.mixins.json",
			"environment": "client"
		}
	],
	"depends": {
		"fabricloader": ">=0.18.4",
		"minecraft": "~1.21.11",
		"java": ">=21",
		"fabric-api": "*"
	}
}
